amulet/anvil/__init__.py
amulet/anvil/__init__.pyi
amulet/anvil/_amulet_anvil.cpython-311-darwin.so
amulet/anvil/_amulet_anvil.pyi
amulet/anvil/_version.py
amulet/anvil/amulet_anvilConfig.cmake
amulet/anvil/dimension.hpp
amulet/anvil/dimension.pyi
amulet/anvil/dll.hpp
amulet/anvil/libamulet_anvil.dylib
amulet/anvil/py.typed
amulet/anvil/region.hpp
amulet/anvil/region.pyi
amulet/anvil/sector_manager.hpp
amulet/anvil/__pyinstaller/__init__.py
amulet/anvil/__pyinstaller/hook-amulet.anvil.py
amulet_anvil-1.0.3a1.dist-info/METADATA
amulet_anvil-1.0.3a1.dist-info/WHEEL
amulet_anvil-1.0.3a1.dist-info/entry_points.txt
amulet_anvil-1.0.3a1.dist-info/top_level.txt
amulet_anvil-1.0.3a1.dist-info/RECORD
