Metadata-Version: 2.4
Name: amulet-anvil
Version: 1.0.3a1
Summary: A C++ library with Python wrapper for the Minecraft Anvil format.
Author: James Clare
Project-URL: Homepage, https://www.amuletmc.com
Project-URL: Repository, https://github.com/Amulet-Team/Amulet-Anvil
Project-URL: Issues, https://github.com/Amulet-Team/Amulet-Anvil/issues
Classifier: Programming Language :: Python :: 3
Classifier: Operating System :: OS Independent
Requires-Python: >=3.11
Requires-Dist: amulet-compiler-target==2.0
Requires-Dist: amulet-compiler-version==4.309027957683952396889703.17
Requires-Dist: pybind11==3.0.0
Requires-Dist: amulet-pybind11-extensions~=1.2.0.0a0
Requires-Dist: amulet-io~=1.0
Requires-Dist: amulet-utils~=1.1.3.0a0
Requires-Dist: amulet-zlib~=1.0.8.0a0
Requires-Dist: amulet-nbt~=5.0.2.0a0
Provides-Extra: dev
Requires-Dist: setuptools>=42; extra == "dev"
Requires-Dist: types-setuptools; extra == "dev"
Requires-Dist: versioneer; extra == "dev"
Requires-Dist: types-versioneer; extra == "dev"
Requires-Dist: packaging; extra == "dev"
Requires-Dist: wheel; extra == "dev"
Requires-Dist: pybind11_stubgen>=2.5.4; extra == "dev"
Requires-Dist: black>=22.3; extra == "dev"
Requires-Dist: isort; extra == "dev"
Requires-Dist: autoflake; extra == "dev"
Requires-Dist: mypy; extra == "dev"
Requires-Dist: types-pyinstaller; extra == "dev"
Requires-Dist: amulet-test-utils~=1.3; extra == "dev"
Dynamic: requires-dist
